ardexaplugin.py
ardexaplugin-0.2.3.dist-info/METADATA
ardexaplugin-0.2.3.dist-info/RECORD
ardexaplugin-0.2.3.dist-info/WHEEL
ardexaplugin-0.2.3.dist-info/top_level.txt
