Metadata-Version: 2.1
Name: ardexaplugin
Version: 0.2.3
Summary: A suite of common tools for developing Ardexa Plugins
Home-page: https://github.com/ardexa/ardexaplugin
Author: Ardexa Pty Limited
Author-email: support@ardexa.com
License: UNKNOWN
Project-URL: Bug Reports, https://github.com/ardexa/ardexaplugin/issues
Project-URL: Source, https://github.com/ardexa/ardexaplugin/
Keywords: development iot ardexa
Platform: UNKNOWN
Classifier: Development Status :: 4 - Beta
Classifier: Intended Audience :: Developers
Classifier: License :: OSI Approved :: MIT License
Classifier: Programming Language :: Python :: 2
Classifier: Programming Language :: Python :: 2.7
Classifier: Programming Language :: Python :: 3
Classifier: Programming Language :: Python :: 3.4
Classifier: Programming Language :: Python :: 3.5
Classifier: Programming Language :: Python :: 3.6
Requires-Python: >=2.7
